LICENSE.md
README.md
pyproject.toml
setup.cfg
setup.py
rds/contrib/__init__.py
rds/contrib/datasus/__init__.py
rds/contrib/datasus/transformers/__init__.py
rds/contrib/datasus/transformers/fields/__init__.py
rds/core/__init__.py
rds/core/cache/__init__.py
rds/core/cache/base.py
rds/core/cache/inmemory.py
rds/core/cache/nocache.py
rds/core/cache/search_engine.py
rds/core/config/__init__.py
rds/core/helpers/__init__.py
rds/core/helpers/http_client.py
rds/core/searchengine/__init__.py
rds/core/transformers/__init__.py
rds/core/transformers/fields/__init__.py
rds/core/transformers/models/__init__.py
rds/core/types/__init__.py
rds/core/validators/__init__.py
rds_core.egg-info/PKG-INFO
rds_core.egg-info/SOURCES.txt
rds_core.egg-info/dependency_links.txt
rds_core.egg-info/requires.txt
rds_core.egg-info/top_level.txt